[
    {
        "id": "1",
        "subject": "Device not connecting to the network",
        "description": "Bernard reports that his computer is not connecting to the network.",
        "contact": {
            "name": "Bernard Bean", 
            "address": "123 Fake Street, Stafford, ST16 3DD",
            "phoneNumber": "02352 543456",
            "contactMethodPreference": "MS Teams",
            "organisation": "bernard inc"  
        },
        "assetNumber": "ABC123456",
        "loggedDate" : "12/10/2022",
        "loggedBy": "Haydn Atkinson",
        "category": "AB11 - Networking & monitoring",
        "classification": "Incident",
        "impact": "Medium",
        "priority": "5 - Routine",
        "status": "live",
        "team": "Network and Systems",
        "leadTech": "Haydn Atkinson" 
    },
    {
        "id": "2",
        "subject": "SCCM deployment is failing with error code 0x000cg2a",
        "description": "John reports that when he tries to install Chrome via software centre, he is getting the error 0x000cg2a",
        "contact": {
            "name": "John Doe", 
            "address": "5 Example Avenue, Newcastle, ST5 3EB",
            "phoneNumber": "02352 543456",
            "contactMethodPreference": "MS Teams",
            "organisation": "John Doe Inc"  
        },
        "assetNumber": "DEF123456",
        "loggedDate" : "07/30/2023",
        "loggedBy": "Haydn Atkinson",
        "category": "AB27 - Device Configuration",
        "classification": "Incident",
        "impact": "Medium",
        "priority": "3 - High",
        "status": "live",
        "team": "Operational Development",
        "leadTech": "Bernard Bean" 
    },
      {
        "id": "3",
        "subject": "Phone divert not working",
        "description": "John reports that the phone 7305850 is not diverting to his mobile",
        "contact": {
            "name": "John Doe", 
            "address": "5 Example Avenue, Newcastle, ST5 3EB",
            "phoneNumber": "02352 543456",
            "contactMethodPreference": "MS Teams",
            "organisation": "John Doe Inc"  
        },
        "assetNumber": "DEF123456",
        "loggedDate" : "07/30/2023",
        "loggedBy": "Haydn Atkinson",
        "category": "AB27 - IPT Fault",
        "classification": "Incident",
        "impact": "Medium",
        "priority": "3 - High",
        "status": "live",
        "team": "Network and Systems",
        "leadTech": "Haydn Atkinson" 
    },
      {
        "id": "4",
        "subject": "Hard drive is full on Johns device",
        "description": "John called to report that his hard drive is full",
        "contact": {
            "name": "John Doe", 
            "address": "5 Example Avenue, Newcastle, ST5 3EB",
            "phoneNumber": "02352 543456",
            "contactMethodPreference": "MS Teams",
            "organisation": "John Doe Inc"  
        },
        "assetNumber": "DEF123456",
        "loggedDate" : "07/30/2023",
        "loggedBy": "Haydn Atkinson",
        "category": "AB27 - Device Configuration",
        "classification": "Incident",
        "impact": "Medium",
        "priority": "3 - High",
        "status": "live",
        "team": "Remote Support",
        "leadTech": "Bernard Bean" 
    },
      {
        "id": "5",
        "subject": "New ethernet cable required",
        "description": "Johns ethernet cable is damaged and he requires a replacement",
        "contact": {
            "name": "John Doe", 
            "address": "5 Example Avenue, Newcastle, ST5 3EB",
            "phoneNumber": "02352 543456",
            "contactMethodPreference": "MS Teams",
            "organisation": "John Doe Inc"  
        },
        "assetNumber": "DEF123456",
        "loggedDate" : "07/30/2023",
        "loggedBy": "Haydn Atkinson",
        "category": "AB27 - Device Configuration",
        "classification": "Incident",
        "impact": "Medium",
        "priority": "3 - High",
        "status": "live",
        "team": "Second Line",
        "leadTech": "Bernard Bean" 
    },
      {
        "id": "6",
        "subject": "I'm running out of subject lines",
        "description": "an example description",
        "contact": {
            "name": "John Doe", 
            "address": "5 Example Avenue, Newcastle, ST5 3EB",
            "phoneNumber": "02352 543456",
            "contactMethodPreference": "MS Teams",
            "organisation": "John Doe Inc"  
        },
        "assetNumber": "DEF123456",
        "loggedDate" : "07/30/2023",
        "loggedBy": "Haydn Atkinson",
        "category": "AB27 - Device Configuration",
        "classification": "Incident",
        "impact": "Medium",
        "priority": "3 - High",
        "status": "live",
        "team": "Operational Development",
        "leadTech": "Bernard Bean" 
    },
      {
        "id": "7",
        "subject": "a new subject",
        "description": "an example description",
        "contact": {
            "name": "John Doe", 
            "address": "5 Example Avenue, Newcastle, ST5 3EB",
            "phoneNumber": "02352 543456",
            "contactMethodPreference": "MS Teams",
            "organisation": "John Doe Inc"  
        },
        "assetNumber": "DEF123456",
        "loggedDate" : "07/30/2023",
        "loggedBy": "Haydn Atkinson",
        "category": "AB27 - Device Configuration",
        "classification": "Incident",
        "impact": "Medium",
        "priority": "3 - High",
        "status": "live",
        "team": "Operational Development",
        "leadTech": "Bernard Bean" 
    },
      {
        "id": "8",
        "subject": "a new subject",
        "description": "an example description",
        "contact": {
            "name": "John Doe", 
            "address": "5 Example Avenue, Newcastle, ST5 3EB",
            "phoneNumber": "02352 543456",
            "contactMethodPreference": "MS Teams",
            "organisation": "John Doe Inc"  
        },
        "assetNumber": "DEF123456",
        "loggedDate" : "07/30/2023",
        "loggedBy": "Haydn Atkinson",
        "category": "AB27 - Device Configuration",
        "classification": "Incident",
        "impact": "Medium",
        "priority": "3 - High",
        "status": "live",
        "team": "Operational Development",
        "leadTech": "Bernard Bean" 
    },
      {
        "id": "9",
        "subject": "a new subject",
        "description": "an example description",
        "contact": {
            "name": "John Doe", 
            "address": "5 Example Avenue, Newcastle, ST5 3EB",
            "phoneNumber": "02352 543456",
            "contactMethodPreference": "MS Teams",
            "organisation": "John Doe Inc"  
        },
        "assetNumber": "DEF123456",
        "loggedDate" : "07/30/2023",
        "loggedBy": "Haydn Atkinson",
        "category": "AB27 - Device Configuration",
        "classification": "Incident",
        "impact": "Medium",
        "priority": "3 - High",
        "status": "live",
        "team": "Operational Development",
        "leadTech": "Bernard Bean" 
    },
      {
        "id": "10",
        "subject": "a new subject",
        "description": "an example description",
        "contact": {
            "name": "John Doe", 
            "address": "5 Example Avenue, Newcastle, ST5 3EB",
            "phoneNumber": "02352 543456",
            "contactMethodPreference": "MS Teams",
            "organisation": "John Doe Inc"  
        },
        "assetNumber": "DEF123456",
        "loggedDate" : "07/30/2023",
        "loggedBy": "Haydn Atkinson",
        "category": "AB27 - Device Configuration",
        "classification": "Incident",
        "impact": "Medium",
        "priority": "3 - High",
        "status": "live",
        "team": "Operational Development",
        "leadTech": "Bernard Bean" 
    }  
]
